topgen/__init__.py
topgen/__main__.py
topgen/payload.proto
topgen/payload_pb2.py
topgen/payload_pb2.pyi
topgen-0.1.1.dist-info/LICENSE
topgen-0.1.1.dist-info/METADATA
topgen-0.1.1.dist-info/WHEEL
topgen-0.1.1.dist-info/RECORD
