Metadata-Version: 2.1
Name: topgen
Version: 0.1.1
Summary: Time-based one-time password generator
Home-page: https://github.com/byildiz/topgen
License: MIT
Keywords: totp,totp-generator,totp-cli,google-authenticator
Author: Burak Yildiz
Author-email: 0byldz@gmail.com
Requires-Python: >=3.10
Classifier: License :: OSI Approved :: MIT License
Classifier: Programming Language :: Python :: 3
Classifier: Programming Language :: Python :: 3.10
Classifier: Programming Language :: Python :: 3.11
Classifier: Programming Language :: Python :: 3.12
Classifier: Topic :: Security :: Cryptography
Classifier: Topic :: Utilities
Requires-Dist: protobuf (==5.28.0)
Requires-Dist: tqdm (>=4.66.1,<5.0.0)
